{"stats":{"minecraft:used":{"minecraft:stone_sword":96,"minecraft:stone_shovel":36,"minecraft:chest":1,"minecraft:iron_sword":225,"minecraft:torch":16,"minecraft:dirt":68,"minecraft:carrot":9,"minecraft:tuff":41,"minecraft:granite":1,"minecraft:iron_axe":78,"minecraft:cooked_cod":37,"minecraft:cobbled_deepslate":535,"minecraft:water_bucket":23,"minecraft:cobblestone_stairs":124,"minecraft:powered_rail":1,"minecraft:stone_pickaxe":266,"minecraft:oak_planks":10,"minecraft:wooden_pickaxe":26,"minecraft:birch_boat":1,"minecraft:salmon":18,"minecraft:rail":11,"minecraft:crafting_table":1,"minecraft:cod":6,"minecraft:cobbled_deepslate_stairs":1,"minecraft:activator_rail":6,"minecraft:apple":15,"minecraft:string":1,"minecraft:iron_pickaxe":535,"minecraft:stone_axe":43,"minecraft:fishing_rod":123,"minecraft:diamond_sword":78,"minecraft:wooden_sword":1,"minecraft:cobblestone":83,"minecraft:white_banner":1,"minecraft:bucket":24},"minecraft:broken":{"minecraft:leather_leggings":1,"minecraft:leather_chestplate":1,"minecraft:iron_sword":1,"minecraft:iron_pickaxe":1,"minecraft:fishing_rod":3,"minecraft:golden_chestplate":1},"minecraft:custom":{"minecraft:interact_with_anvil":2,"minecraft:mob_kills":53,"minecraft:interact_with_crafting_table":47,"minecraft:bell_ring":231,"minecraft:leave_game":4,"minecraft:time_since_death":55442,"minecraft:climb_one_cm":5763,"minecraft:sprint_one_cm":1021673,"minecraft:walk_one_cm":1437349,"minecraft:drop":47,"minecraft:talked_to_villager":3,"minecraft:play_time":339625,"minecraft:sneak_time":53,"minecraft:deaths":18,"minecraft:walk_under_water_one_cm":176602,"minecraft:boat_one_cm":180641,"minecraft:jump":4359,"minecraft:walk_on_water_one_cm":130282,"minecraft:total_world_time":339625,"minecraft:interact_with_furnace":15,"minecraft:sleep_in_bed":1,"minecraft:time_since_rest":55484,"minecraft:damage_taken":7428,"minecraft:damage_dealt":7429,"minecraft:swim_one_cm":65510,"minecraft:fly_one_cm":259607,"minecraft:open_chest":298,"minecraft:crouch_one_cm":615,"minecraft:fish_caught":49,"minecraft:fall_one_cm":87196},"minecraft:crafted":{"minecraft:wooden_sword":1,"minecraft:oak_planks":294,"minecraft:stone_shovel":2,"minecraft:fishing_rod":1,"minecraft:cobblestone_stairs":124,"minecraft:bow":1,"minecraft:iron_axe":1,"minecraft:wooden_shovel":1,"minecraft:diamond_sword":1,"minecraft:crafting_table":1,"minecraft:wooden_pickaxe":3,"minecraft:wooden_hoe":1,"minecraft:stick":32,"minecraft:iron_ingot":9,"minecraft:iron_pickaxe":2,"minecraft:wooden_axe":2},"minecraft:killed_by":{"minecraft:player":2,"minecraft:wolf":1,"minecraft:creeper":1,"minecraft:ravager":1,"minecraft:cave_spider":1,"minecraft:skeleton":6,"minecraft:zombie":3},"minecraft:mined":{"minecraft:tuff":41,"minecraft:deepslate_diamond_ore":6,"minecraft:cobbled_deepslate_stairs":1,"minecraft:cobblestone_stairs":5,"minecraft:granite":1,"minecraft:grass_block":67,"minecraft:oxeye_daisy":1,"minecraft:iron_ore":1,"minecraft:cobbled_deepslate":39,"minecraft:andesite":1,"minecraft:deepslate_lapis_ore":4,"minecraft:deepslate_iron_ore":11,"minecraft:dirt_path":2,"minecraft:rail":9,"minecraft:stone":189,"minecraft:tripwire":1,"minecraft:deepslate_redstone_ore":2,"minecraft:dandelion":6,"minecraft:oak_fence":7,"minecraft:cornflower":2,"minecraft:torch":2,"minecraft:tall_grass":127,"minecraft:cobblestone":8,"minecraft:deepslate_gold_ore":26,"minecraft:sugar_cane":3,"minecraft:oak_planks":77,"minecraft:wall_torch":7,"minecraft:grass":500,"minecraft:oak_log":42,"minecraft:coal_ore":28,"minecraft:sand":14,"minecraft:dirt":21,"minecraft:cobweb":92,"minecraft:gold_ore":3,"minecraft:oak_leaves":3,"minecraft:deepslate":456},"minecraft:killed":{"minecraft:vex":1,"minecraft:cave_spider":15,"minecraft:spider":2,"minecraft:slime":8,"minecraft:skeleton":3,"minecraft:bat":1,"minecraft:pillager":3,"minecraft:zombie":20},"minecraft:dropped":{"minecraft:water_bucket":1,"minecraft:enchanted_book":1,"minecraft:iron_sword":5,"minecraft:lapis_lazuli":20,"minecraft:oak_log":5,"minecraft:glass_bottle":3,"minecraft:cobblestone":7,"minecraft:oak_fence":10,"minecraft:rail":7,"minecraft:stick":46,"minecraft:diorite":1,"minecraft:crimson_roots":2,"minecraft:cooked_cod":23,"minecraft:iron_pickaxe":5,"minecraft:string":134,"minecraft:fishing_rod":1,"minecraft:stone_axe":1,"minecraft:stone_sword":3,"minecraft:raw_copper":45,"minecraft:raw_iron":2,"minecraft:rotten_flesh":4,"minecraft:carrot":8,"minecraft:andesite":1,"minecraft:arrow":2,"minecraft:wooden_pickaxe":1,"minecraft:stone_pickaxe":3,"minecraft:raw_gold":4},"minecraft:picked_up":{"minecraft:wooden_axe":1,"minecraft:fishing_rod":4,"minecraft:leather_leggings":1,"minecraft:diamond_sword":2,"minecraft:wooden_pickaxe":2,"minecraft:enchanted_book":1,"minecraft:shield":1,"minecraft:cornflower":2,"minecraft:string":250,"minecraft:raw_copper":92,"minecraft:iron_axe":2,"minecraft:cooked_salmon":59,"minecraft:wooden_sword":2,"minecraft:pufferfish":1,"minecraft:oak_sign":16,"minecraft:activator_rail":15,"minecraft:cobbled_deepslate":801,"minecraft:bucket":8,"minecraft:oak_boat":1,"minecraft:poppy":2,"minecraft:wooden_shovel":2,"minecraft:iron_pickaxe":19,"minecraft:minecart":2,"minecraft:sugar_cane":7,"minecraft:chest":1,"minecraft:stick":386,"minecraft:raw_iron":12,"minecraft:oak_fence":22,"minecraft:torch":17,"minecraft:bowl":2,"minecraft:diorite":1,"minecraft:carrot":2,"minecraft:redstone":18,"minecraft:golden_chestplate":1,"minecraft:stone_sword":5,"minecraft:cooked_cod":84,"minecraft:arrow":18,"minecraft:rotten_flesh":63,"minecraft:tropical_fish":3,"minecraft:cod":33,"minecraft:rail":38,"minecraft:cobblestone":297,"minecraft:oxeye_daisy":1,"minecraft:leather_chestplate":1,"minecraft:glow_ink_sac":3,"minecraft:water_bucket":5,"minecraft:andesite":1,"minecraft:salmon":33,"minecraft:leather":2,"minecraft:birch_planks":1,"minecraft:tuff":132,"minecraft:oak_log":110,"minecraft:cobbled_deepslate_stairs":1,"minecraft:gunpowder":4,"minecraft:cobblestone_stairs":21,"minecraft:lapis_lazuli":76,"minecraft:dirt":147,"minecraft:white_banner":1,"minecraft:leather_boots":1,"minecraft:bone":8,"minecraft:apple":49,"minecraft:wheat_seeds":66,"minecraft:raw_gold":33,"minecraft:stone_pickaxe":8,"minecraft:iron_ingot":6,"minecraft:glass_bottle":3,"minecraft:powered_rail":3,"minecraft:iron_sword":11,"minecraft:oak_planks":273,"minecraft:soul_sand":1,"minecraft:birch_boat":1,"minecraft:dandelion":6,"minecraft:sand":14,"minecraft:spider_eye":1,"minecraft:slime_ball":14,"minecraft:diamond":13,"minecraft:stone_axe":2,"minecraft:granite":21,"minecraft:emerald":1,"minecraft:oak_sapling":4,"minecraft:coal":28,"minecraft:crimson_roots":2}},"DataVersion":2975}